LICENSE
MANIFEST.in
README.md
setup.py
peepdis/__init__.py
peepdis/core.py
peepdis/datastructures.py
peepdis/legacy.py
peepdis/preferences.py
peepdis.egg-info/PKG-INFO
peepdis.egg-info/SOURCES.txt
peepdis.egg-info/dependency_links.txt
peepdis.egg-info/requires.txt
peepdis.egg-info/top_level.txt