Metadata-Version: 1.1
Name: peepdis
Version: 0.1.11
Summary: Terminal object inspector for python
Home-page: https://github.com/TheAustinator/peep-dis
Author: Austin McKay
Author-email: austinmckay303@gmail.com
License: MIT License
